enaml_native_maps.py
enaml_native_maps-1.2.data/data/packages/enaml-native-maps/android/.gitignore
enaml_native_maps-1.2.data/data/packages/enaml-native-maps/android/build.gradle
enaml_native_maps-1.2.data/data/packages/enaml-native-maps/android/gradlew
enaml_native_maps-1.2.data/data/packages/enaml-native-maps/android/gradlew.bat
enaml_native_maps-1.2.data/data/packages/enaml-native-maps/android/local.properties
enaml_native_maps-1.2.data/data/packages/enaml-native-maps/android/proguard-rules.pro
enaml_native_maps-1.2.data/data/packages/enaml-native-maps/android/gradle/wrapper/gradle-wrapper.jar
enaml_native_maps-1.2.data/data/packages/enaml-native-maps/android/gradle/wrapper/gradle-wrapper.properties
enaml_native_maps-1.2.data/data/packages/enaml-native-maps/android/src/main/AndroidManifest.xml
enaml_native_maps-1.2.data/data/packages/enaml-native-maps/android/src/main/java/com/codelv/enamlnative/packages/GoogleMapsPackage.java
enaml_native_maps-1.2.data/data/packages/enaml-native-maps/src/setup.py
enaml_native_maps-1.2.data/data/packages/enaml-native-maps/src/googlemaps/__init__.py
enaml_native_maps-1.2.data/data/packages/enaml-native-maps/src/googlemaps/android/__init__.py
enaml_native_maps-1.2.data/data/packages/enaml-native-maps/src/googlemaps/android/android_map_view.py
enaml_native_maps-1.2.data/data/packages/enaml-native-maps/src/googlemaps/android/factories.py
enaml_native_maps-1.2.data/data/packages/enaml-native-maps/src/googlemaps/widgets/__init__.py
enaml_native_maps-1.2.data/data/packages/enaml-native-maps/src/googlemaps/widgets/api.py
enaml_native_maps-1.2.data/data/packages/enaml-native-maps/src/googlemaps/widgets/map_view.py
enaml_native_maps-1.2.dist-info/DESCRIPTION.rst
enaml_native_maps-1.2.dist-info/METADATA
enaml_native_maps-1.2.dist-info/RECORD
enaml_native_maps-1.2.dist-info/WHEEL
enaml_native_maps-1.2.dist-info/entry_points.txt
enaml_native_maps-1.2.dist-info/metadata.json
enaml_native_maps-1.2.dist-info/top_level.txt
