Metadata-Version: 2.0
Name: enaml-native-maps
Version: 1.2
Summary: enaml-native-maps package for enaml-native-cli
Home-page: https://github.com/codelv/enaml-native-maps
Author: CodeLV
Author-email: frmdstryr@gmail.com
License: MIT
Platform: UNKNOWN
Requires-Dist: enaml-native (>=3.0.0)
